pyswagger/__init__.py
pyswagger/core.py
pyswagger/errs.py
pyswagger/getter.py
pyswagger/io.py
pyswagger/resolve.py
pyswagger/scan.py
pyswagger/utils.py
pyswagger/consts/__init__.py
pyswagger/consts/private.py
pyswagger/contrib/__init__.py
pyswagger/contrib/client/__init__.py
pyswagger/contrib/client/flask.py
pyswagger/contrib/client/requests.py
pyswagger/contrib/client/tornado.py
pyswagger/contrib/client/webapp2.py
pyswagger/primitives/__init__.py
pyswagger/primitives/_array.py
pyswagger/primitives/_bool.py
pyswagger/primitives/_byte.py
pyswagger/primitives/_file.py
pyswagger/primitives/_float.py
pyswagger/primitives/_int.py
pyswagger/primitives/_model.py
pyswagger/primitives/_str.py
pyswagger/primitives/_time.py
pyswagger/primitives/_uuid.py
pyswagger/primitives/codec.py
pyswagger/primitives/comm.py
pyswagger/primitives/render.py
pyswagger/scanner/__init__.py
pyswagger/scanner/cycle_detector.py
pyswagger/scanner/type_reducer.py
pyswagger/scanner/v1_2/__init__.py
pyswagger/scanner/v1_2/upgrade.py
pyswagger/scanner/v1_2/validate.py
pyswagger/scanner/v2_0/__init__.py
pyswagger/scanner/v2_0/aggt.py
pyswagger/scanner/v2_0/assign_parent.py
pyswagger/scanner/v2_0/merge.py
pyswagger/scanner/v2_0/norm_ref.py
pyswagger/scanner/v2_0/patch_obj.py
pyswagger/scanner/v2_0/resolve.py
pyswagger/scanner/v2_0/validate.py
pyswagger/scanner/v2_0/yaml.py
pyswagger/spec/__init__.py
pyswagger/spec/base.py
pyswagger/spec/v1_2/__init__.py
pyswagger/spec/v1_2/objects.py
pyswagger/spec/v1_2/parser.py
pyswagger/spec/v2_0/__init__.py
pyswagger/spec/v2_0/objects.py
pyswagger/spec/v2_0/parser.py
pyswagger/tests/__init__.py
pyswagger/tests/test_base.py
pyswagger/tests/test_codec.py
pyswagger/tests/test_core.py
pyswagger/tests/test_getter.py
pyswagger/tests/test_render.py
pyswagger/tests/test_utils.py
pyswagger/tests/test_yaml.py
pyswagger/tests/utils.py
pyswagger-0.8.39.dist-info/METADATA
pyswagger-0.8.39.dist-info/RECORD
pyswagger-0.8.39.dist-info/WHEEL
pyswagger-0.8.39.dist-info/top_level.txt
