Metadata-Version: 1.1
Name: pyswagger
Version: 0.8.39
Summary: A type-safe, dynamic, spec-compliant swagger client & converter for python
Home-page: https://github.com/mission-liao/pyswagger
Author: Mission Liao
Author-email: missionaryliao@gmail.com
License: UNKNOWN
Download-URL: https://github.com/mission-liao/pyswagger/tarball/0.8.39
Keywords: swagger,REST
Platform: UNKNOWN
Classifier: Development Status :: 4 - Beta
Classifier: Intended Audience :: Developers
Classifier: License :: OSI Approved :: MIT License
Classifier: Operating System :: OS Independent
Classifier: Programming Language :: Python :: 2.6
Classifier: Programming Language :: Python :: 2.7
Classifier: Programming Language :: Python :: 3.3
Classifier: Programming Language :: Python :: 3.4
Classifier: Topic :: Software Development :: Libraries :: Python Modules
